README.md
setup.py
Pointillism.egg-info/PKG-INFO
Pointillism.egg-info/SOURCES.txt
Pointillism.egg-info/dependency_links.txt
Pointillism.egg-info/requires.txt
Pointillism.egg-info/top_level.txt
pointillism/__init__.py
pointillism/batch.py
pointillism/image.py
pointillism/pipeline.py
pointillism.egg-info/PKG-INFO
pointillism.egg-info/SOURCES.txt
pointillism.egg-info/dependency_links.txt
pointillism.egg-info/requires.txt
pointillism.egg-info/top_level.txt