Metadata-Version: 2.1
Name: pointillism
Version: 0.1.5
Summary: Pointillism-style photo manipulation package
Home-page: https://github.com/tsennott/pointillism
Author: Tim Sennott
Author-email: timothy.sennott@gmail.com
License: MIT
Keywords: image manipulation art photos pointillism illustration graphics
Platform: UNKNOWN
Classifier: Programming Language :: Python :: 3.6
Classifier: Programming Language :: Python :: 3.5
Classifier: Programming Language :: Python :: 3.4
Classifier: Programming Language :: Python :: 2.7
Classifier: License :: OSI Approved :: MIT License
Classifier: Operating System :: OS Independent
